yes/__init__.py
yes-0.0.1.dist-info/METADATA
yes-0.0.1.dist-info/RECORD
yes-0.0.1.dist-info/WHEEL
yes-0.0.1.dist-info/top_level.txt
